pyros_api
