Metadata-Version: 2.1
Name: pyros-api
Version: 0.1.2
Summary: A simplified routerOS api in python!
Home-page: https://github.com/cykyy/pyros-api
Author: Rayhan Mia
Author-email: miarayhan11@icloud.com
License: MIT
Project-URL: Documentation, https://github.com/cykyy/pyros-api
Project-URL: Source Code, https://github.com/cykyy/pyros-api
Keywords: routerOS,mikrotik,routeros-api,routeros-python-api
Platform: UNKNOWN
Classifier: Development Status :: 5 - Production/Stable
Classifier: License :: OSI Approved :: MIT License
Classifier: Operating System :: OS Independent
Classifier: Programming Language :: Python
Classifier: Programming Language :: Python :: 2
Classifier: Programming Language :: Python :: 2.7
Classifier: Programming Language :: Python :: 3
Classifier: Programming Language :: Python :: 3.4
Classifier: Programming Language :: Python :: 3.5
Classifier: Programming Language :: Python :: 3.6
Classifier: Programming Language :: Python :: 3.7
